nester_pasaribu.py
setup.py
test_spasaribu.egg-info/PKG-INFO
test_spasaribu.egg-info/SOURCES.txt
test_spasaribu.egg-info/dependency_links.txt
test_spasaribu.egg-info/top_level.txt