Metadata-Version: 2.1
Name: test-spasaribu
Version: 0.1.0
Summary: A small example package
Home-page: https://github.com/pypa/sampleproject
Author: Sepanya Pasaribu
Author-email: sepanyapasaribu@gmail.com
License: UNKNOWN
Platform: UNKNOWN
Classifier: Programming Language :: Python :: 3
Classifier: License :: OSI Approved :: MIT License
Classifier: Operating System :: OS Independent
Requires-Python: >=3.6
